MANIFEST.in
README.rst
setup.py
data/coveragerc
data/pytest.ini
pytest_config/__init__.py
pytest_config/fixtures.py
pytest_config/logger.py
pytest_config/models.py
pytest_config/plugin.py
pytest_config/pretty.py
pytest_config/views.py
pytest_config.egg-info/PKG-INFO
pytest_config.egg-info/SOURCES.txt
pytest_config.egg-info/dependency_links.txt
pytest_config.egg-info/entry_points.txt
pytest_config.egg-info/not-zip-safe
pytest_config.egg-info/requires.txt
pytest_config.egg-info/top_level.txt
pytest_config/_templates/config_section_not_found.txt
pytest_config/_templates/outdated_conf_file.txt
scripts/pytest_config.init
scripts/pytest_config.update