Metadata-Version: 1.1
Name: pytest-config
Version: 0.0.10
Summary: 
Home-page: https://github.com/buzzfeed/pytest_config
Author: Gerardo Orozco Mosqueda
Author-email: gerard.mosqueda@buzzfeed.com
License: UNKNOWN
Platform: UNKNOWN
Classifier: Development Status :: 5 - Production/Stable
Classifier: Framework :: Django
Classifier: Intended Audience :: Developers
Classifier: License :: OSI Approved :: BSD License
Classifier: Natural Language :: English
Classifier: Programming Language :: Python :: 2
Classifier: Programming Language :: Python :: 2.6
Classifier: Programming Language :: Python :: 2.7
Classifier: Programming Language :: Python :: 3
Classifier: Programming Language :: Python :: 3.3
